qrzlib/__init__.py
qrzlib/_version.py
qrzlib/py.typed
qrzlib-2.0.5.dist-info/licenses/LICENSE
qrzlib-2.0.5.dist-info/METADATA
qrzlib-2.0.5.dist-info/WHEEL
qrzlib-2.0.5.dist-info/entry_points.txt
qrzlib-2.0.5.dist-info/top_level.txt
qrzlib-2.0.5.dist-info/RECORD
