Metadata-Version: 2.4
Name: qrzlib
Version: 2.0.5
Summary: API to access data from qrz.com.
Author: Fred C. (W6BSD)
License: BSD 3-Clause License
Project-URL: Source, https://github.com/0x9900/qrzlib
Project-URL: Tracker, https://github.com/0x9900/qrzlib/issues
Classifier: Development Status :: 4 - Beta
Classifier: Intended Audience :: Developers
Classifier: Intended Audience :: Telecommunications Industry
Classifier: License :: OSI Approved :: BSD License
Classifier: Operating System :: OS Independent
Classifier: Programming Language :: Python :: 3
Classifier: Programming Language :: Python
Classifier: Topic :: Communications :: Ham Radio
Requires-Python: >=3.10
License-File: LICENSE
Dynamic: license-file
